lecroyparser/__init__.py
lecroyparser-1.4.2.dist-info/LICENSE
lecroyparser-1.4.2.dist-info/METADATA
lecroyparser-1.4.2.dist-info/WHEEL
lecroyparser-1.4.2.dist-info/top_level.txt
lecroyparser-1.4.2.dist-info/RECORD
