Metadata-Version: 2.1
Name: lecroyparser
Version: 1.4.2
Summary: Parse LeCroy Binary Files.
Home-page: http://github.com/bennomeier/lecroyparser
Author: Benno Meier
Author-email: meier.benno@gmail.com
License: MIT
Keywords: LeCroy Binary Scope Parse
Platform: UNKNOWN
Classifier: License :: OSI Approved :: MIT License
Classifier: Programming Language :: Python
Classifier: Topic :: Scientific/Engineering :: Physics
Requires-Dist: numpy
